{
  "key": "plugin_content_manager_configuration_components::question.free-text-question",
  "value": {
    "settings": {
      "bulkable": true,
      "filterable": true,
      "searchable": true,
      "pageSize": 10,
      "mainField": "title",
      "defaultSortBy": "title",
      "defaultSortOrder": "ASC"
    },
    "metadatas": {
      "id": {
        "edit": {},
        "list": {
          "label": "id",
          "searchable": false,
          "sortable": false
        }
      },
      "title": {
        "edit": {
          "label": "title",
          "description": "",
          "placeholder": "",
          "visible": true,
          "editable": true
        },
        "list": {
          "label": "title",
          "searchable": true,
          "sortable": true
        }
      },
      "code": {
        "edit": {
          "label": "code",
          "description": "",
          "placeholder": "",
          "visible": true,
          "editable": true
        },
        "list": {
          "label": "code",
          "searchable": true,
          "sortable": true
        }
      },
      "type": {
        "edit": {
          "label": "type",
          "description": "",
          "placeholder": "",
          "visible": true,
          "editable": true
        },
        "list": {
          "label": "type",
          "searchable": true,
          "sortable": true
        }
      }
    },
    "layouts": {
      "list": [
        "id",
        "title",
        "code",
        "type"
      ],
      "edit": [
        [
          {
            "name": "title",
            "size": 6
          },
          {
            "name": "code",
            "size": 6
          }
        ],
        [
          {
            "name": "type",
            "size": 6
          }
        ]
      ]
    },
    "uid": "question.free-text-question",
    "isComponent": true
  },
  "type": "object",
  "environment": null,
  "tag": null
}